odoo/addons/sale_pricelist_from_commitment_date/README.rst
odoo/addons/sale_pricelist_from_commitment_date/__init__.py
odoo/addons/sale_pricelist_from_commitment_date/__manifest__.py
odoo/addons/sale_pricelist_from_commitment_date/i18n/es.po
odoo/addons/sale_pricelist_from_commitment_date/i18n/fr.po
odoo/addons/sale_pricelist_from_commitment_date/i18n/it.po
odoo/addons/sale_pricelist_from_commitment_date/i18n/sale_pricelist_from_commitment_date.pot
odoo/addons/sale_pricelist_from_commitment_date/models/__init__.py
odoo/addons/sale_pricelist_from_commitment_date/models/product_pricelist.py
odoo/addons/sale_pricelist_from_commitment_date/models/product_pricelist_item.py
odoo/addons/sale_pricelist_from_commitment_date/models/sale_order_line.py
odoo/addons/sale_pricelist_from_commitment_date/readme/CONTRIBUTORS.rst
odoo/addons/sale_pricelist_from_commitment_date/readme/DESCRIPTION.rst
odoo/addons/sale_pricelist_from_commitment_date/static/description/icon.png
odoo/addons/sale_pricelist_from_commitment_date/static/description/index.html
odoo/addons/sale_pricelist_from_commitment_date/tests/__init__.py
odoo/addons/sale_pricelist_from_commitment_date/tests/test_pricelist_from_commitment_date.py
odoo_addon_sale_pricelist_from_commitment_date-16.0.1.0.0.8.dist-info/METADATA
odoo_addon_sale_pricelist_from_commitment_date-16.0.1.0.0.8.dist-info/WHEEL
odoo_addon_sale_pricelist_from_commitment_date-16.0.1.0.0.8.dist-info/top_level.txt
odoo_addon_sale_pricelist_from_commitment_date-16.0.1.0.0.8.dist-info/RECORD
